{
    "nb_items": 20,
    "nb_reticles": 55,
    "nb_machines": 14,
    "nb_periods": 3,
    "L": 1440,
    "ST": 5,
    "TT": 30,
    "B": 56.25,
    "D": [
        [
            29,
            27,
            30
        ],
        [
            39,
            31,
            36
        ],
        [
            25,
            42,
            37
        ],
        [
            45,
            42,
            42
        ],
        [
            31,
            36,
            44
        ],
        [
            44,
            36,
            45
        ],
        [
            43,
            29,
            38
        ],
        [
            30,
            30,
            33
        ],
        [
            35,
            29,
            41
        ],
        [
            39,
            45,
            42
        ],
        [
            39,
            36,
            43
        ],
        [
            39,
            40,
            30
        ],
        [
            28,
            38,
            30
        ],
        [
            30,
            26,
            38
        ],
        [
            32,
            41,
            32
        ],
        [
            41,
            28,
            33
        ],
        [
            35,
            28,
            40
        ],
        [
            30,
            36,
            34
        ],
        [
            37,
            35,
            30
        ],
        [
            39,
            39,
            29
        ]
    ],
    "PT": [
        25,
        23,
        21,
        24,
        20,
        24,
        21,
        20,
        21,
        21,
        22,
        22,
        22,
        20,
        22,
        21,
        20,
        20,
        21,
        25
    ],
    "SC": [
        89,
        89,
        83,
        52,
        52,
        67,
        54,
        53,
        56,
        56,
        64,
        92,
        68,
        89,
        97,
        88,
        57,
        77,
        69,
        75
    ],
    "HC": [
        63,
        50,
        57,
        58,
        55,
        55,
        61,
        75,
        59,
        59,
        61,
        58,
        53,
        63,
        54,
        57,
        62,
        68,
        61,
        50
    ],
    "BC": [
        120,
        138,
        200,
        103,
        121,
        128,
        120,
        154,
        137,
        172,
        120,
        167,
        109,
        151,
        124,
        110,
        175,
        156,
        197,
        121
    ],
    "Ri": [
        [
            0,
            1,
            2
        ],
        [
            3,
            4,
            5
        ],
        [
            6,
            7,
            8
        ],
        [
            9,
            10,
            11
        ],
        [
            12,
            13,
            14
        ],
        [
            15,
            16,
            17
        ],
        [
            18,
            19,
            20
        ],
        [
            21,
            22,
            23
        ],
        [
            24,
            25,
            26
        ],
        [
            27,
            28,
            29
        ],
        [
            30,
            31,
            32
        ],
        [
            33,
            34,
            35
        ],
        [
            36,
            37,
            38
        ],
        [
            39,
            40,
            41
        ],
        [
            42,
            43,
            44
        ],
        [
            45,
            46
        ],
        [
            47,
            48
        ],
        [
            49,
            50
        ],
        [
            51,
            52
        ],
        [
            53,
            54
        ]
    ]
}